{"skeleton":{"hash":"A+PG03gctpo","spine":"4.1.24","x":-164.76,"y":-42,"width":279.76,"height":235.31,"images":"./texture/","audio":"C:/RookissArt/Art/ani/mob/wild boar/psd"},"bones":[{"name":"root"},{"name":"center","parent":"root","x":-7.42,"y":45.25},{"name":"body","parent":"center","length":49.56,"rotation":142.24,"x":74.78,"y":0.28},{"name":"body_2","parent":"body","length":55,"rotation":14.41,"x":49.78,"y":0.17},{"name":"head","parent":"body_2","length":98.83,"rotation":55.58,"x":56.56,"y":1.27},{"name":"l_leg_f","parent":"body_2","length":55.77,"rotation":111.36,"x":14.78,"y":29.82},{"name":"r_leg_f","parent":"body_2","length":53.58,"rotation":101.46,"x":51.84,"y":42.82},{"name":"l_leg_b","parent":"body","length":55.51,"rotation":150.89,"x":11.21,"y":-10.86},{"name":"r_leg_b","parent":"body","length":51.73,"rotation":143.62,"x":35.49,"y":5.89},{"name":"l_ear","parent":"head","length":55.69,"rotation":162.71,"x":-11.93,"y":-21.51},{"name":"r_ear","parent":"head","length":30.86,"rotation":-70.33,"x":21.22,"y":-42.41},{"name":"shadow","parent":"root","color":"ff0000ff"},{"name":"l_leg_b_ik","parent":"root","x":87.16,"y":9.93,"color":"ff3f00ff"},{"name":"l_leg_f_ik","parent":"root","x":0.8,"y":-1.38,"color":"ff3f00ff"},{"name":"r_leg_f_ik","parent":"root","x":-47.49,"y":4.69,"color":"ff3f00ff"},{"name":"r_leg_b_ik","parent":"root","x":50.46,"y":10.2,"color":"ff3f00ff"}],"slots":[{"name":"shadow","bone":"shadow","attachment":"shadow"},{"name":"r_leg_b","bone":"r_leg_b","attachment":"r_leg_b"},{"name":"r_leg_f","bone":"r_leg_f","attachment":"r_leg_f"},{"name":"body","bone":"body","attachment":"body"},{"name":"r_ear","bone":"r_ear","attachment":"r_ear"},{"name":"head","bone":"head","attachment":"head"},{"name":"l_leg_b","bone":"l_leg_b","attachment":"l_leg_b"},{"name":"l_leg_f","bone":"l_leg_f","attachment":"l_leg_f"},{"name":"l_ear","bone":"l_ear","attachment":"l_ear"},{"name":"head_attack","bone":"root"}],"ik":[{"name":"l_leg_b_ik","bones":["l_leg_b"],"target":"l_leg_b_ik","compress":true,"stretch":true},{"name":"l_leg_f_ik","order":1,"bones":["l_leg_f"],"target":"l_leg_f_ik","compress":true,"stretch":true},{"name":"r_leg_b_ik","order":3,"bones":["r_leg_b"],"target":"r_leg_b_ik","compress":true,"stretch":true},{"name":"r_leg_f_ik","order":2,"bones":["r_leg_f"],"target":"r_leg_f_ik","compress":true,"stretch":true}],"skins":[{"name":"default","attachments":{"body":{"body":{"type":"mesh","uvs":[0.65171,0.07421,0.86236,0.29869,0.94199,0.45903,0.99999,0.65956,0.97576,0.85466,0.82805,0.98604,0.63763,0.99999,0.45345,0.98836,0.28436,0.93715,0.11808,0.84007,0,0.60333,0,0.40605,0.06761,0.14124,0.25096,0,0.4539,0,0.09936,0.48194,0.2019,0.19091,0.28766,0.62844,0.42003,0.26538,0.42562,0.7192,0.54307,0.31891,0.57104,0.79368,0.6773,0.40269,0.75374,0.83091,0.83204,0.51906],"triangles":[7,21,6,6,23,5,6,21,23,8,19,7,7,19,21,5,23,4,8,17,19,8,9,17,4,23,3,10,15,9,9,15,17,23,24,3,23,21,24,21,22,24,21,19,22,19,17,20,19,20,22,20,17,18,24,2,3,15,16,17,17,16,18,10,11,15,24,1,2,24,22,1,15,11,16,16,11,12,1,22,0,22,20,0,0,20,14,16,13,18,20,18,14,18,13,14,16,12,13],"vertices":[2,2,97.78,-64.32,0.14058,3,30.43,-74.4,0.85942,2,2,46.32,-61.87,0.67515,3,-18.8,-59.22,0.32485,2,2,19.98,-52.05,0.93249,3,-41.87,-43.16,0.06751,1,2,-6.85,-35.04,1,1,2,-21.09,-9.3,1,2,2,-11.36,23,0.99147,3,-53.53,37.33,0.00853,2,2,15.37,46.33,0.75897,3,-21.84,53.28,0.24103,2,2,43.52,65.95,0.31027,3,10.3,65.27,0.68973,2,2,73.05,79.17,0.072,3,42.2,70.73,0.928,2,2,106.36,86.68,0.00421,3,76.33,69.7,0.99579,1,3,110.47,46.02,1,1,3,122.12,19.03,1,1,3,126.22,-22.18,1,1,3,103.25,-55.01,1,2,2,133.63,-50.53,0.01522,3,68.59,-69.97,0.98478,1,3,100.68,22.09,1,1,3,100.35,-25.28,1,2,2,100.74,42.43,0.00378,3,59.87,28.25,0.99622,2,2,114.4,-15.41,0.0065,3,58.71,-31.17,0.9935,2,2,72.17,37.41,0.07843,3,30.95,30.5,0.92157,2,2,91.42,-23.12,0.06373,3,34.53,-32.92,0.93627,2,2,43.99,29.62,0.48832,3,1.72,29.96,0.51168,2,2,64.04,-28.54,0.36971,3,6.66,-31.35,0.63029,2,2,13.73,13.19,0.97819,3,-31.68,21.59,0.02181,2,2,30.67,-32.46,0.92865,3,-26.63,-26.84,0.07135],"hull":15,"edges":[26,24,24,22,20,22,20,18,18,16,16,14,12,14,10,12,10,8,8,6,6,4,4,2,2,0,26,28,0,28],"width":186,"height":149}},"head":{"head":{"x":33.85,"y":-18.01,"rotation":147.77,"width":204,"height":198},"head_attack":{"x":33.85,"y":-18.01,"rotation":147.77,"width":204,"height":198}},"l_ear":{"l_ear":{"x":22.81,"y":-2.33,"rotation":-14.93,"width":71,"height":44}},"l_leg_b":{"l_leg_b":{"x":16.93,"y":1.01,"rotation":66.88,"width":63,"height":79}},"l_leg_f":{"l_leg_f":{"x":18.89,"y":4.88,"rotation":91.98,"width":53,"height":80}},"r_ear":{"r_ear":{"x":8.25,"y":-1.32,"rotation":-141.9,"width":48,"height":47}},"r_leg_b":{"r_leg_b":{"x":15.34,"y":-2.35,"rotation":74.46,"width":50,"height":78}},"r_leg_f":{"r_leg_f":{"x":18.04,"y":3.19,"rotation":101.89,"width":47,"height":75}},"shadow":{"shadow":{"width":230,"height":84}}}}],"events":{"event_attack":{}},"animations":{"attack":{"slots":{"head":{"attachment":[{"time":0.5,"name":"head_attack"},{"time":0.8,"name":"head"}]}},"bones":{"center":{"translate":[{"curve":[0.111,0,0.244,13.13,0.111,0,0.223,6.82]},{"time":0.3333,"x":18.94,"y":-3.08,"curve":[0.367,21.09,0.4,24.17,0.399,-8.94,0.381,-6.94]},{"time":0.4333,"x":24.17,"y":-19.34,"curve":[0.456,24.17,0.478,-31.01,0.487,-32.09,0.472,-17.45]},{"time":0.5,"x":-30.56,"y":-7.74,"curve":[0.544,-29.65,0.589,-31.46,0.6,26.55,0.552,1.1]},{"time":0.6333,"x":-30.56,"y":1.1,"curve":[0.804,-27.07,0.881,0,0.767,1.1,0.9,0]},{"time":1.0333}]},"body_2":{"rotate":[{"curve":[0.111,0,0.222,1.56]},{"time":0.3333,"value":5.16,"curve":[0.367,6.24,0.4,14.03]},{"time":0.4333,"value":14.03,"curve":[0.456,14.03,0.478,-5.82]},{"time":0.5,"value":-5.82,"curve":"stepped"},{"time":0.6333,"value":-5.82,"curve":[0.786,-5.82,0.881,0]},{"time":1.0333}]},"head":{"rotate":[{"curve":[0.111,0,0.222,3.03]},{"time":0.3333,"value":5.64,"curve":[0.367,6.42,0.4,10.15]},{"time":0.4333,"value":10.15,"curve":[0.456,10.15,0.478,-76.18]},{"time":0.5,"value":-76.18,"curve":"stepped"},{"time":0.6333,"value":-76.18,"curve":[0.786,-76.18,0.881,0]},{"time":1.0333}]},"r_leg_f":{"rotate":[{}]},"l_leg_b":{"rotate":[{}]},"r_leg_b":{"rotate":[{}]},"l_ear":{"rotate":[{"time":0.4333,"curve":[0.456,0,0.478,0.93]},{"time":0.5,"value":0.93,"curve":"stepped"},{"time":0.6333,"value":0.93,"curve":[0.786,0.93,0.881,0]},{"time":1.0333}]},"r_ear":{"rotate":[{"time":0.4333,"curve":[0.456,0,0.478,-45.24]},{"time":0.5,"value":-45.24,"curve":"stepped"},{"time":0.6333,"value":-45.24,"curve":[0.786,-45.24,0.881,0]},{"time":1.0333}]}},"events":[{"time":0.5,"name":"event_attack"}]},"dead":{"bones":{"center":{"rotate":[{"curve":[0.044,0,0.089,24.48]},{"time":0.1333,"value":24.48,"curve":"stepped"},{"time":0.4,"value":24.48,"curve":[0.444,24.48,0.489,16.2]},{"time":0.5333,"value":16.2,"curve":[0.578,16.2,0.622,24.48]},{"time":0.6667,"value":24.48,"curve":"stepped"},{"time":0.8,"value":24.48,"curve":[0.856,24.48,0.911,11.32]},{"time":0.9667,"value":11.32}],"translate":[{"curve":[0.044,0,0.089,40.6,0.044,0,0.046,28.74]},{"time":0.1333,"x":51.75,"y":34.85,"curve":[0.222,74.05,0.311,84.96,0.322,48.1,0.311,-48.58]},{"time":0.4,"x":100.33,"y":-48.58,"curve":[0.444,108.02,0.489,113.83,0.444,-48.58,0.452,6.87]},{"time":0.5333,"x":120.93,"y":11.04,"curve":[0.578,128.03,0.622,137.41,0.617,15.36,0.622,-45.34]},{"time":0.6667,"x":142.91,"y":-45.34,"curve":[0.711,148.4,0.756,151.33,0.711,-45.34,0.756,-34.93]},{"time":0.8,"x":153.9,"y":-34.93,"curve":[0.856,157.11,0.911,160.26,0.856,-34.93,0.911,-44.18]},{"time":0.9667,"x":160.26,"y":-44.18,"curve":[1.022,160.26,1.078,160.26,1.022,-44.18,1.078,-44.18]},{"time":1.1333,"x":160.26,"y":-44.18}]},"body":{"rotate":[{"time":0.1333,"curve":[0.222,0,0.311,0]},{"time":0.4,"curve":[0.444,0,0.489,0]},{"time":0.5333,"curve":[0.578,0,0.622,0]},{"time":0.6667,"curve":[0.711,0,0.756,0]},{"time":0.8,"curve":[0.856,0,0.911,0]},{"time":0.9667,"curve":[1.022,0,1.078,0]},{"time":1.1333}]},"body_2":{"rotate":[{"curve":[0.044,0,0.089,-22.01]},{"time":0.1333,"value":-22.01,"curve":"stepped"},{"time":0.4,"value":-22.01,"curve":[0.444,-22.01,0.489,-6.18]},{"time":0.5333,"value":-6.18,"curve":[0.578,-6.18,0.622,-14.09]},{"time":0.6667,"value":-14.09,"curve":[0.711,-14.09,0.756,-14.09]},{"time":0.8,"value":-13.85,"curve":[0.856,-13.56,0.911,-2.03]},{"time":0.9667,"value":-2.03}]},"head":{"rotate":[{"curve":[0.044,0,0.089,-42.09]},{"time":0.1333,"value":-44.87,"curve":[0.222,-50.42,0.311,-50.42]},{"time":0.4,"value":-50.42,"curve":[0.444,-50.42,0.489,-30.13]},{"time":0.5333,"value":-30.13,"curve":[0.578,-30.13,0.622,-47.63]},{"time":0.6667,"value":-47.63,"curve":[0.711,-47.63,0.756,-47.63]},{"time":0.8,"value":-43.65,"curve":[0.856,-38.68,0.911,-18.16]},{"time":0.9667,"value":-18.16}]},"l_leg_f":{"rotate":[{"curve":[0.044,0,0.089,-41.64]},{"time":0.1333,"value":-54.87,"curve":[0.222,-81.32,0.311,-119.02]},{"time":0.4,"value":-119.02,"curve":[0.444,-119.02,0.489,-64.07]},{"time":0.5333,"value":-64.07,"curve":[0.578,-64.07,0.622,-104.19]},{"time":0.6667,"value":-104.19,"curve":[0.711,-104.19,0.756,-100.18]},{"time":0.8,"value":-98.17,"curve":[0.856,-95.65,0.911,-90.6]},{"time":0.9667,"value":-90.6}]},"r_leg_f":{"rotate":[{"curve":[0.044,0,0.089,-49.46]},{"time":0.1333,"value":-61.55,"curve":[0.222,-85.73,0.311,-108.81]},{"time":0.4,"value":-108.81,"curve":[0.444,-108.81,0.489,-49.96]},{"time":0.5333,"value":-49.96,"curve":[0.578,-49.96,0.622,-98.18]},{"time":0.6667,"value":-98.18,"curve":[0.711,-98.18,0.756,-87.57]},{"time":0.8,"value":-87.25,"curve":[0.856,-86.84,0.911,-86.84]},{"time":0.9667,"value":-86.84}]},"l_leg_b":{"rotate":[{"curve":[0.044,0,0.089,32.44]},{"time":0.1333,"value":39.56,"curve":[0.222,53.78,0.311,64.02]},{"time":0.4,"value":64.02,"curve":[0.444,64.02,0.489,-3.2]},{"time":0.5333,"value":-3.2,"curve":[0.578,-3.2,0.622,41.73]},{"time":0.6667,"value":41.73,"curve":[0.711,41.73,0.756,17.78]},{"time":0.8,"value":17.24,"curve":[0.856,16.55,0.911,16.55]},{"time":0.9667,"value":16.55,"curve":[1.022,16.55,1.078,16.55]},{"time":1.1333,"value":16.55}]},"r_leg_b":{"rotate":[{"curve":[0.044,0,0.089,22.18]},{"time":0.1333,"value":29.6,"curve":[0.222,44.45,0.311,66.82]},{"time":0.4,"value":66.82,"curve":[0.444,66.82,0.489,-4.81]},{"time":0.5333,"value":-4.81,"curve":[0.578,-4.81,0.622,62.92]},{"time":0.6667,"value":62.92,"curve":[0.711,62.92,0.756,40.51]},{"time":0.8,"value":34.91,"curve":[0.856,27.92,0.911,25.17]},{"time":0.9667,"value":25.17}]},"shadow":{"translate":[{"curve":[0.044,0,0.089,34.86,0.044,0,0.089,0]},{"time":0.1333,"x":34.86,"curve":[0.222,34.86,0.311,85.61,0.222,0,0.311,0]},{"time":0.4,"x":85.61},{"time":0.5333,"x":108.35},{"time":0.6667,"x":132.93},{"time":0.8,"x":136.62}]}},"ik":{"l_leg_b_ik":[{"mix":0,"compress":true,"stretch":true,"curve":[0.044,0,0.089,0,0.044,0,0.089,0]},{"time":0.1333,"mix":0,"compress":true,"stretch":true,"curve":[0.222,0,0.311,0,0.222,0,0.311,0]},{"time":0.4,"mix":0,"compress":true,"stretch":true,"curve":[0.444,0,0.489,0,0.444,0,0.489,0]},{"time":0.5333,"mix":0,"compress":true,"stretch":true,"curve":[0.578,0,0.622,0,0.578,0,0.622,0]},{"time":0.6667,"mix":0,"compress":true,"stretch":true,"curve":[0.711,0,0.756,0,0.711,0,0.756,0]},{"time":0.8,"mix":0,"compress":true,"stretch":true,"curve":[0.856,0,0.911,0,0.856,0,0.911,0]},{"time":0.9667,"mix":0,"compress":true,"stretch":true,"curve":[1.022,0,1.078,0,1.022,0,1.078,0]},{"time":1.1333,"mix":0,"compress":true,"stretch":true}],"l_leg_f_ik":[{"mix":0,"compress":true,"stretch":true,"curve":[0.044,0,0.089,0,0.044,0,0.089,0]},{"time":0.1333,"mix":0,"compress":true,"stretch":true,"curve":[0.222,0,0.311,0,0.222,0,0.311,0]},{"time":0.4,"mix":0,"compress":true,"stretch":true,"curve":[0.444,0,0.489,0,0.444,0,0.489,0]},{"time":0.5333,"mix":0,"compress":true,"stretch":true,"curve":[0.578,0,0.622,0,0.578,0,0.622,0]},{"time":0.6667,"mix":0,"compress":true,"stretch":true,"curve":[0.711,0,0.756,0,0.711,0,0.756,0]},{"time":0.8,"mix":0,"compress":true,"stretch":true,"curve":[0.856,0,0.911,0,0.856,0,0.911,0]},{"time":0.9667,"mix":0,"compress":true,"stretch":true,"curve":[1.022,0,1.078,0,1.022,0,1.078,0]},{"time":1.1333,"mix":0,"compress":true,"stretch":true}],"r_leg_b_ik":[{"mix":0,"compress":true,"stretch":true,"curve":[0.044,0,0.089,0,0.044,0,0.089,0]},{"time":0.1333,"mix":0,"compress":true,"stretch":true,"curve":[0.222,0,0.311,0,0.222,0,0.311,0]},{"time":0.4,"mix":0,"compress":true,"stretch":true,"curve":[0.444,0,0.489,0,0.444,0,0.489,0]},{"time":0.5333,"mix":0,"compress":true,"stretch":true,"curve":[0.578,0,0.622,0,0.578,0,0.622,0]},{"time":0.6667,"mix":0,"compress":true,"stretch":true,"curve":[0.711,0,0.756,0,0.711,0,0.756,0]},{"time":0.8,"mix":0,"compress":true,"stretch":true,"curve":[0.856,0,0.911,0,0.856,0,0.911,0]},{"time":0.9667,"mix":0,"compress":true,"stretch":true,"curve":[1.022,0,1.078,0,1.022,0,1.078,0]},{"time":1.1333,"mix":0,"compress":true,"stretch":true}],"r_leg_f_ik":[{"mix":0,"compress":true,"stretch":true,"curve":[0.044,0,0.089,0,0.044,0,0.089,0]},{"time":0.1333,"mix":0,"compress":true,"stretch":true,"curve":[0.222,0,0.311,0,0.222,0,0.311,0]},{"time":0.4,"mix":0,"compress":true,"stretch":true,"curve":[0.444,0,0.489,0,0.444,0,0.489,0]},{"time":0.5333,"mix":0,"compress":true,"stretch":true,"curve":[0.578,0,0.622,0,0.578,0,0.622,0]},{"time":0.6667,"mix":0,"compress":true,"stretch":true,"curve":[0.711,0,0.756,0,0.711,0,0.756,0]},{"time":0.8,"mix":0,"compress":true,"stretch":true,"curve":[0.856,0,0.911,0,0.856,0,0.911,0]},{"time":0.9667,"mix":0,"compress":true,"stretch":true,"curve":[1.022,0,1.078,0,1.022,0,1.078,0]},{"time":1.1333,"mix":0,"compress":true,"stretch":true}]}},"idle":{"bones":{"center":{"translate":[{"curve":[0.167,0,0.333,0,0.167,0,0.333,-0.29]},{"time":0.5,"y":-0.29,"curve":[0.667,0,0.833,0,0.667,-0.29,0.833,0]},{"time":1}]},"body_2":{"rotate":[{"curve":[0.167,0,0.333,6.73]},{"time":0.5,"value":6.73,"curve":[0.667,6.73,0.833,0]},{"time":1}]},"head":{"rotate":[{"curve":[0.167,0,0.333,-5.1]},{"time":0.5,"value":-5.1,"curve":[0.667,-5.1,0.833,0]},{"time":1}]},"r_leg_f":{"rotate":[{}]},"l_leg_b":{"rotate":[{}]},"r_leg_b":{"rotate":[{}]},"l_ear":{"rotate":[{"time":0.5,"curve":[0.556,0,0.611,16.58]},{"time":0.6667,"value":16.58,"curve":[0.7,16.58,0.733,-7.04]},{"time":0.7667,"value":-7.04,"curve":[0.789,-7.04,0.811,11.38]},{"time":0.8333,"value":11.38,"curve":[0.889,11.38,0.944,0]},{"time":1}]},"r_ear":{"rotate":[{"time":0.5,"curve":[0.556,0,0.611,-18.77]},{"time":0.6667,"value":-18.77,"curve":[0.7,-18.77,0.733,34.07]},{"time":0.7667,"value":34.07,"curve":[0.789,34.07,0.811,-8.1]},{"time":0.8333,"value":-8.1,"curve":[0.889,-8.1,0.944,0]},{"time":1}]}}},"move":{"bones":{"center":{"rotate":[{"time":0.1667,"curve":[0.209,0,0.258,13.74]},{"time":0.3,"value":13.74,"curve":[0.37,13.74,0.43,0]},{"time":0.5}],"translate":[{"curve":[0.056,0,0.111,0,0.056,0,0.111,0]},{"time":0.1667,"y":3.76,"curve":[0.209,0,0.258,0,0.209,6.57,0.217,39.06]},{"time":0.3,"y":40.03,"curve":[0.37,0,0.43,0,0.446,41.75,0.43,0]},{"time":0.5}]},"body":{"rotate":[{"time":0.1667,"curve":[0.209,0,0.258,0.13]},{"time":0.3,"value":0.13,"curve":[0.37,0.13,0.43,0]},{"time":0.5}]},"body_2":{"rotate":[{"curve":[0.056,0,0.113,-1.07]},{"time":0.1667,"value":-5.44,"curve":[0.208,-8.82,0.216,-15.82]},{"time":0.3,"value":-15.77,"curve":[0.43,-15.7,0.415,-0.82]},{"time":0.5}]},"head":{"rotate":[{"time":0.1667,"curve":[0.209,0,0.258,-23.42]},{"time":0.3,"value":-23.07,"curve":[0.377,-22.43,0.43,0]},{"time":0.5}]},"l_leg_f":{"rotate":[{"value":26.13,"curve":[0.056,26.13,0.111,-24.27]},{"time":0.1667,"value":-46.35,"curve":[0.209,-62.9,0.258,-89.75]},{"time":0.3,"value":-89.75,"curve":[0.37,-89.75,0.43,26.13]},{"time":0.5,"value":26.13}]},"r_leg_f":{"rotate":[{"value":28.24,"curve":[0.056,28.24,0.111,-17.54]},{"time":0.1667,"value":-37.45,"curve":[0.209,-52.37,0.258,-76.26]},{"time":0.3,"value":-76.26,"curve":[0.37,-76.26,0.43,28.24]},{"time":0.5,"value":28.24}]},"l_leg_b":{"rotate":[{"value":-38.61,"curve":[0.056,-38.61,0.111,1]},{"time":0.1667,"value":18.14,"curve":[0.209,31,0.258,51.39]},{"time":0.3,"value":51.39,"curve":[0.37,51.39,0.43,-38.61]},{"time":0.5,"value":-38.61}]},"r_leg_b":{"rotate":[{"value":-30.41,"curve":[0.056,-30.41,0.111,9.88]},{"time":0.1667,"value":28.16,"curve":[0.209,41.87,0.258,65.57]},{"time":0.3,"value":65.57,"curve":[0.37,65.57,0.43,-30.41]},{"time":0.5,"value":-30.41}]},"l_ear":{"rotate":[{"curve":[0.056,0,0.111,-5.15]},{"time":0.1667,"value":-5.15,"curve":[0.209,-5.15,0.258,-0.08]},{"time":0.3,"value":-0.05,"curve":[0.37,0,0.43,0]},{"time":0.5}]},"r_ear":{"rotate":[{"curve":[0.056,0,0.111,-21.82]},{"time":0.1667,"value":-32.84,"curve":[0.209,-41.1,0.258,-57.82]},{"time":0.3,"value":-57.82,"curve":[0.37,-57.82,0.43,0]},{"time":0.5}]}},"ik":{"l_leg_b_ik":[{"mix":0,"compress":true,"stretch":true,"curve":[0.098,0,0.202,0,0.098,0,0.202,0]},{"time":0.3,"mix":0,"compress":true,"stretch":true,"curve":[0.37,0,0.43,0,0.37,0,0.43,0]},{"time":0.5,"mix":0,"compress":true,"stretch":true}],"l_leg_f_ik":[{"mix":0,"compress":true,"stretch":true,"curve":[0.098,0,0.202,0,0.098,0,0.202,0]},{"time":0.3,"mix":0,"compress":true,"stretch":true,"curve":[0.37,0,0.43,0,0.37,0,0.43,0]},{"time":0.5,"mix":0,"compress":true,"stretch":true}],"r_leg_b_ik":[{"mix":0,"compress":true,"stretch":true,"curve":[0.098,0,0.202,0,0.098,0,0.202,0]},{"time":0.3,"mix":0,"compress":true,"stretch":true,"curve":[0.37,0,0.43,0,0.37,0,0.43,0]},{"time":0.5,"mix":0,"compress":true,"stretch":true}],"r_leg_f_ik":[{"mix":0,"compress":true,"stretch":true,"curve":[0.098,0,0.202,0,0.098,0,0.202,0]},{"time":0.3,"mix":0,"compress":true,"stretch":true,"curve":[0.37,0,0.43,0,0.37,0,0.43,0]},{"time":0.5,"mix":0,"compress":true,"stretch":true}]}}}}